setup.py
django_formtags.egg-info/PKG-INFO
django_formtags.egg-info/SOURCES.txt
django_formtags.egg-info/dependency_links.txt
django_formtags.egg-info/not-zip-safe
django_formtags.egg-info/top_level.txt
formtags/__init__.py
formtags/utils.py
formtags/templatetags/__init__.py
formtags/templatetags/formtags.py
tests/__init__.py
tests/forms.py
tests/settings.py
tests/test_formtags.py