Metadata-Version: 1.0
Name: django-formtags
Version: 0.1.2
Summary: Customize form fields directly from templates
Home-page: https://github.com/bmispelon/django-formtags/
Author: Baptiste Mispelon
Author-email: bmispelon@gmail.com
License: BSD
Keywords: django,forms,tags
Platform: UNKNOWN
Classifier: Programming Language :: Python
Classifier: Topic :: Software Development :: Libraries :: Python Modules
Classifier: Framework :: Django
Classifier: Environment :: Web Environment
Classifier: Programming Language :: Python :: 2.6
Classifier: Programming Language :: Python :: 2.7
Classifier: Programming Language :: Python :: 3.2
Classifier: Programming Language :: Python :: 3.3
